{
  "stage": "D3",
  "graph_cdm": {
    "implemented": true,
    "d_pred": "ground_truth_label_based",
    "d_neigh": "KL_label_space",
    "d_view": "mode_disagreement",
    "d_chain": "temporal_similarity"
  },
  "evidence": {
    "freq_protect": "log",
    "anom_source": "recon_error",
    "normalized": true
  },
  "weights": {
    "w_min": 0.0,
    "w_distribution": "stable"
  },
  "ranking": {
    "topk_functional": true,
    "stable_topk": true
  },
  "loss": {
    "cls_integrated": true,
    "convergence": true
  },
  "coLD_degeneracy": {
    "rho_zero_behaviour_matches_baseline": true
  },
  "determinism": {
    "seed_42_reproducible": true
  }
}
